open3d_python-0.7.0.0.data/data/etc/jupyter/nbconfig/notebook.d/enable_jupyter_extension.json
open3d_python-0.7.0.0.data/data/share/jupyter/nbextensions/open3d/12c8482249da928cedbafe8c3d624c0b.png
open3d_python-0.7.0.0.data/data/share/jupyter/nbextensions/open3d/extension.js
open3d_python-0.7.0.0.data/data/share/jupyter/nbextensions/open3d/index.js
open3d_python-0.7.0.0.data/data/share/jupyter/nbextensions/open3d/index.js.map
open3d_python-0.7.0.0.data/purelib/open3d/__init__.py
open3d_python-0.7.0.0.data/purelib/open3d/j_visualizer.py
open3d_python-0.7.0.0.data/purelib/open3d/open3d.cp37-win_amd64.pyd
open3d_python-0.7.0.0.data/purelib/open3d/static/12c8482249da928cedbafe8c3d624c0b.png
open3d_python-0.7.0.0.data/purelib/open3d/static/extension.js
open3d_python-0.7.0.0.data/purelib/open3d/static/index.js
open3d_python-0.7.0.0.data/purelib/open3d/static/index.js.map
open3d_python-0.7.0.0.dist-info/LICENSE.txt
open3d_python-0.7.0.0.dist-info/METADATA
open3d_python-0.7.0.0.dist-info/WHEEL
open3d_python-0.7.0.0.dist-info/top_level.txt
open3d_python-0.7.0.0.dist-info/RECORD
